
[
  {
    "label": "category",
    "filter": [
      { "id": "channel branding", "display": "channel branding" },
      { "id": "format design", "display": "format design" },
      { "id": "content graphics", "display": "content graphics" },
      { "id": "idents & labels", "display": "idents & labels" },
      { "id": "event design", "display": "event design" },
      { "id": "visual storytelling", "display": "visual storytelling" }
    ]
  },

  {
    "label": "expertise",
    "filter": [
      { "id": "concept", "display": "concept" },
      { "id": "design", "display": "design" },
      { "id": "animation", "display": "animation" },
      { "id": "3d", "display": "3D" },
      { "id": "compositing", "display": "compositing" },
      { "id": "editing", "display": "editing" }
    ]
  }
]